[
  {
    "name": "f8c491d390c0d0608009",
    "expression": {
      "Column": {
        "Expression": {
          "SourceRef": {
            "Entity": "ref_client"
          }
        },
        "Property": "ClientName"
      }
    },
    "filter": {
      "Version": 2,
      "From": [
        {
          "Name": "r",
          "Entity": "ref_client",
          "Type": 0
        }
      ],
      "Where": [
        {
          "Condition": {
            "Not": {
              "Expression": {
                "In": {
                  "Expressions": [
                    {
                      "Column": {
                        "Expression": {
                          "SourceRef": {
                            "Source": "r"
                          }
                        },
                        "Property": "ClientName"
                      }
                    }
                  ],
                  "Values": [
                    [
                      {
                        "Literal": {
                          "Value": "null"
                        }
                      }
                    ]
                  ]
                }
              }
            }
          }
        }
      ]
    },
    "type": "Categorical",
    "howCreated": 0,
    "objects": {
      "general": [
        {
          "properties": {
            "isInvertedSelectionMode": {
              "expr": {
                "Literal": {
                  "Value": "true"
                }
              }
            }
          }
        }
      ]
    },
    "isHiddenInViewMode": false
  }
]